pklxml/__init__.py
pklxml/deserializer.py
pklxml/serializer.py
pklxml-0.2.3.dist-info/licenses/LICENSE
pklxml-0.2.3.dist-info/METADATA
pklxml-0.2.3.dist-info/WHEEL
pklxml-0.2.3.dist-info/top_level.txt
pklxml-0.2.3.dist-info/RECORD
