Metadata-Version: 2.4
Name: pklxml
Version: 0.2.3
Summary: A human-readable and secure XML-based alternative to pickle.
Author: RAPTOR7762
License: BSD 2-Clause License
Requires-Python: >=3.8
License-File: LICENSE
Dynamic: license-file
